{
  "timestamp_utc": "2025-12-16T00:03:23.597319Z",
  "database_path": "data/runtime/vx11.db",
  "tables": [
    {
      "name": "audit_logs",
      "rows": 0,
      "status": "EMPTY (READY)",
      "module": "unknown",
      "columns": [
        {
          "name": "id",
          "type": "INTEGER",
          "pk": true,
          "not_null": true,
          "default": null
        },
        {
          "name": "component",
          "type": "VARCHAR(64)",
          "pk": false,
          "not_null": true,
          "default": null
        },
        {
          "name": "level",
          "type": "VARCHAR(16)",
          "pk": false,
          "not_null": false,
          "default": null
        },
        {
          "name": "message",
          "type": "TEXT",
          "pk": false,
          "not_null": true,
          "default": null
        },
        {
          "name": "created_at",
          "type": "DATETIME",
          "pk": false,
          "not_null": false,
          "default": null
        }
      ],
      "foreign_keys": []
    },
    {
      "name": "cli_onboarding_state",
      "rows": 0,
      "status": "EMPTY (READY)",
      "module": "switch",
      "columns": [
        {
          "name": "id",
          "type": "INTEGER",
          "pk": true,
          "not_null": true,
          "default": null
        },
        {
          "name": "provider_id",
          "type": "VARCHAR(128)",
          "pk": false,
          "not_null": true,
          "default": null
        },
        {
          "name": "state",
          "type": "VARCHAR(50)",
          "pk": false,
          "not_null": false,
          "default": null
        },
        {
          "name": "notes",
          "type": "TEXT",
          "pk": false,
          "not_null": false,
          "default": null
        },
        {
          "name": "last_checked_at",
          "type": "DATETIME",
          "pk": false,
          "not_null": false,
          "default": null
        },
        {
          "name": "created_at",
          "type": "DATETIME",
          "pk": false,
          "not_null": false,
          "default": null
        }
      ],
      "foreign_keys": []
    },
    {
      "name": "cli_providers",
      "rows": 0,
      "status": "EMPTY (READY)",
      "module": "switch",
      "columns": [
        {
          "name": "id",
          "type": "INTEGER",
          "pk": true,
          "not_null": true,
          "default": null
        },
        {
          "name": "name",
          "type": "VARCHAR(100)",
          "pk": false,
          "not_null": true,
          "default": null
        },
        {
          "name": "base_url",
          "type": "VARCHAR(500)",
          "pk": false,
          "not_null": false,
          "default": null
        },
        {
          "name": "api_key_env",
          "type": "VARCHAR(100)",
          "pk": false,
          "not_null": true,
          "default": null
        },
        {
          "name": "task_types",
          "type": "VARCHAR(255)",
          "pk": false,
          "not_null": false,
          "default": null
        },
        {
          "name": "daily_limit_tokens",
          "type": "INTEGER",
          "pk": false,
          "not_null": false,
          "default": null
        },
        {
          "name": "monthly_limit_tokens",
          "type": "INTEGER",
          "pk": false,
          "not_null": false,
          "default": null
        },
        {
          "name": "tokens_used_today",
          "type": "INTEGER",
          "pk": false,
          "not_null": false,
          "default": null
        },
        {
          "name": "tokens_used_month",
          "type": "INTEGER",
          "pk": false,
          "not_null": false,
          "default": null
        },
        {
          "name": "reset_hour_utc",
          "type": "INTEGER",
          "pk": false,
          "not_null": false,
          "default": null
        },
        {
          "name": "enabled",
          "type": "BOOLEAN",
          "pk": false,
          "not_null": false,
          "default": null
        },
        {
          "name": "last_reset_at",
          "type": "DATETIME",
          "pk": false,
          "not_null": false,
          "default": null
        },
        {
          "name": "created_at",
          "type": "DATETIME",
          "pk": false,
          "not_null": false,
          "default": null
        },
        {
          "name": "updated_at",
          "type": "DATETIME",
          "pk": false,
          "not_null": false,
          "default": null
        }
      ],
      "foreign_keys": []
    },
    {
      "name": "cli_registry",
      "rows": 0,
      "status": "EMPTY (READY)",
      "module": "hermes",
      "columns": [
        {
          "name": "id",
          "type": "INTEGER",
          "pk": true,
          "not_null": true,
          "default": null
        },
        {
          "name": "name",
          "type": "VARCHAR(100)",
          "pk": false,
          "not_null": true,
          "default": null
        },
        {
          "name": "bin_path",
          "type": "VARCHAR(500)",
          "pk": false,
          "not_null": false,
          "default": null
        },
        {
          "name": "available",
          "type": "BOOLEAN",
          "pk": false,
          "not_null": false,
          "default": null
        },
        {
          "name": "last_checked",
          "type": "DATETIME",
          "pk": false,
          "not_null": false,
          "default": null
        },
        {
          "name": "cli_type",
          "type": "VARCHAR(50)",
          "pk": false,
          "not_null": true,
          "default": null
        },
        {
          "name": "token_config_key",
          "type": "VARCHAR(100)",
          "pk": false,
          "not_null": false,
          "default": null
        },
        {
          "name": "rate_limit_daily",
          "type": "INTEGER",
          "pk": false,
          "not_null": false,
          "default": null
        },
        {
          "name": "used_today",
          "type": "INTEGER",
          "pk": false,
          "not_null": false,
          "default": null
        },
        {
          "name": "notes",
          "type": "TEXT",
          "pk": false,
          "not_null": false,
          "default": null
        },
        {
          "name": "updated_at",
          "type": "DATETIME",
          "pk": false,
          "not_null": false,
          "default": null
        }
      ],
      "foreign_keys": []
    },
    {
      "name": "cli_usage_stats",
      "rows": 1,
      "status": "ACTIVE",
      "module": "switch",
      "columns": [
        {
          "name": "id",
          "type": "INTEGER",
          "pk": true,
          "not_null": true,
          "default": null
        },
        {
          "name": "provider_id",
          "type": "VARCHAR(128)",
          "pk": false,
          "not_null": true,
          "default": null
        },
        {
          "name": "timestamp",
          "type": "DATETIME",
          "pk": false,
          "not_null": false,
          "default": null
        },
        {
          "name": "success",
          "type": "BOOLEAN",
          "pk": false,
          "not_null": false,
          "default": null
        },
        {
          "name": "latency_ms",
          "type": "INTEGER",
          "pk": false,
          "not_null": false,
          "default": null
        },
        {
          "name": "cost_estimated",
          "type": "FLOAT",
          "pk": false,
          "not_null": false,
          "default": null
        },
        {
          "name": "tokens_estimated",
          "type": "INTEGER",
          "pk": false,
          "not_null": false,
          "default": null
        },
        {
          "name": "error_class",
          "type": "VARCHAR(100)",
          "pk": false,
          "not_null": false,
          "default": null
        }
      ],
      "foreign_keys": []
    },
    {
      "name": "context",
      "rows": 0,
      "status": "EMPTY (READY)",
      "module": "madre",
      "columns": [
        {
          "name": "id",
          "type": "INTEGER",
          "pk": true,
          "not_null": true,
          "default": null
        },
        {
          "name": "task_id",
          "type": "VARCHAR(36)",
          "pk": false,
          "not_null": true,
          "default": null
        },
        {
          "name": "key",
          "type": "VARCHAR(255)",
          "pk": false,
          "not_null": true,
          "default": null
        },
        {
          "name": "value",
          "type": "TEXT",
          "pk": false,
          "not_null": true,
          "default": null
        },
        {
          "name": "scope",
          "type": "VARCHAR(50)",
          "pk": false,
          "not_null": false,
          "default": null
        },
        {
          "name": "created_at",
          "type": "DATETIME",
          "pk": false,
          "not_null": false,
          "default": null
        }
      ],
      "foreign_keys": [
        {
          "column": "task_id",
          "references_table": "tasks",
          "references_column": "uuid"
        }
      ]
    },
    {
      "name": "daughter_attempts",
      "rows": 0,
      "status": "EMPTY (READY)",
      "module": "madre",
      "columns": [
        {
          "name": "id",
          "type": "INTEGER",
          "pk": true,
          "not_null": true,
          "default": null
        },
        {
          "name": "daughter_id",
          "type": "INTEGER",
          "pk": false,
          "not_null": true,
          "default": null
        },
        {
          "name": "attempt_number",
          "type": "INTEGER",
          "pk": false,
          "not_null": false,
          "default": null
        },
        {
          "name": "started_at",
          "type": "DATETIME",
          "pk": false,
          "not_null": false,
          "default": null
        },
        {
          "name": "finished_at",
          "type": "DATETIME",
          "pk": false,
          "not_null": false,
          "default": null
        },
        {
          "name": "status",
          "type": "VARCHAR(32)",
          "pk": false,
          "not_null": false,
          "default": null
        },
        {
          "name": "error_message",
          "type": "VARCHAR(500)",
          "pk": false,
          "not_null": false,
          "default": null
        },
        {
          "name": "tokens_used_cli",
          "type": "INTEGER",
          "pk": false,
          "not_null": false,
          "default": null
        },
        {
          "name": "tokens_used_local",
          "type": "INTEGER",
          "pk": false,
          "not_null": false,
          "default": null
        },
        {
          "name": "switch_model_used",
          "type": "VARCHAR(128)",
          "pk": false,
          "not_null": false,
          "default": null
        },
        {
          "name": "cli_provider_used",
          "type": "VARCHAR(128)",
          "pk": false,
          "not_null": false,
          "default": null
        },
        {
          "name": "created_at",
          "type": "DATETIME",
          "pk": false,
          "not_null": false,
          "default": null
        }
      ],
      "foreign_keys": [
        {
          "column": "daughter_id",
          "references_table": "daughters",
          "references_column": "id"
        }
      ]
    },
    {
      "name": "daughter_tasks",
      "rows": 0,
      "status": "EMPTY (READY)",
      "module": "madre",
      "columns": [
        {
          "name": "id",
          "type": "INTEGER",
          "pk": true,
          "not_null": true,
          "default": null
        },
        {
          "name": "intent_id",
          "type": "VARCHAR(36)",
          "pk": false,
          "not_null": false,
          "default": null
        },
        {
          "name": "source",
          "type": "VARCHAR(64)",
          "pk": false,
          "not_null": true,
          "default": null
        },
        {
          "name": "priority",
          "type": "INTEGER",
          "pk": false,
          "not_null": false,
          "default": null
        },
        {
          "name": "status",
          "type": "VARCHAR(32)",
          "pk": false,
          "not_null": false,
          "default": null
        },
        {
          "name": "task_type",
          "type": "VARCHAR(50)",
          "pk": false,
          "not_null": true,
          "default": null
        },
        {
          "name": "description",
          "type": "TEXT",
          "pk": false,
          "not_null": false,
          "default": null
        },
        {
          "name": "created_at",
          "type": "DATETIME",
          "pk": false,
          "not_null": false,
          "default": null
        },
        {
          "name": "updated_at",
          "type": "DATETIME",
          "pk": false,
          "not_null": false,
          "default": null
        },
        {
          "name": "finished_at",
          "type": "DATETIME",
          "pk": false,
          "not_null": false,
          "default": null
        },
        {
          "name": "max_retries",
          "type": "INTEGER",
          "pk": false,
          "not_null": false,
          "default": null
        },
        {
          "name": "current_retry",
          "type": "INTEGER",
          "pk": false,
          "not_null": false,
          "default": null
        },
        {
          "name": "metadata_json",
          "type": "TEXT",
          "pk": false,
          "not_null": false,
          "default": null
        },
        {
          "name": "plan_json",
          "type": "TEXT",
          "pk": false,
          "not_null": false,
          "default": null
        }
      ],
      "foreign_keys": []
    },
    {
      "name": "daughters",
      "rows": 0,
      "status": "EMPTY (READY)",
      "module": "madre",
      "columns": [
        {
          "name": "id",
          "type": "INTEGER",
          "pk": true,
          "not_null": true,
          "default": null
        },
        {
          "name": "task_id",
          "type": "INTEGER",
          "pk": false,
          "not_null": true,
          "default": null
        },
        {
          "name": "name",
          "type": "VARCHAR(128)",
          "pk": false,
          "not_null": true,
          "default": null
        },
        {
          "name": "purpose",
          "type": "TEXT",
          "pk": false,
          "not_null": false,
          "default": null
        },
        {
          "name": "tools_json",
          "type": "TEXT",
          "pk": false,
          "not_null": false,
          "default": null
        },
        {
          "name": "ttl_seconds",
          "type": "INTEGER",
          "pk": false,
          "not_null": false,
          "default": null
        },
        {
          "name": "started_at",
          "type": "DATETIME",
          "pk": false,
          "not_null": false,
          "default": null
        },
        {
          "name": "last_heartbeat_at",
          "type": "DATETIME",
          "pk": false,
          "not_null": false,
          "default": null
        },
        {
          "name": "ended_at",
          "type": "DATETIME",
          "pk": false,
          "not_null": false,
          "default": null
        },
        {
          "name": "status",
          "type": "VARCHAR(32)",
          "pk": false,
          "not_null": false,
          "default": null
        },
        {
          "name": "mutation_level",
          "type": "INTEGER",
          "pk": false,
          "not_null": false,
          "default": null
        },
        {
          "name": "error_last",
          "type": "TEXT",
          "pk": false,
          "not_null": false,
          "default": null
        }
      ],
      "foreign_keys": [
        {
          "column": "task_id",
          "references_table": "daughter_tasks",
          "references_column": "id"
        }
      ]
    },
    {
      "name": "drift_reports",
      "rows": 0,
      "status": "EMPTY (READY)",
      "module": "unknown",
      "columns": [
        {
          "name": "id",
          "type": "INTEGER",
          "pk": true,
          "not_null": true,
          "default": null
        },
        {
          "name": "module",
          "type": "VARCHAR(64)",
          "pk": false,
          "not_null": true,
          "default": null
        },
        {
          "name": "details",
          "type": "TEXT",
          "pk": false,
          "not_null": true,
          "default": null
        },
        {
          "name": "severity",
          "type": "VARCHAR(32)",
          "pk": false,
          "not_null": false,
          "default": null
        },
        {
          "name": "timestamp",
          "type": "DATETIME",
          "pk": false,
          "not_null": false,
          "default": null
        },
        {
          "name": "resolved",
          "type": "BOOLEAN",
          "pk": false,
          "not_null": false,
          "default": null
        }
      ],
      "foreign_keys": []
    },
    {
      "name": "engines",
      "rows": 0,
      "status": "EMPTY (READY)",
      "module": "switch",
      "columns": [
        {
          "name": "id",
          "type": "INTEGER",
          "pk": true,
          "not_null": true,
          "default": null
        },
        {
          "name": "name",
          "type": "VARCHAR(128)",
          "pk": false,
          "not_null": true,
          "default": null
        },
        {
          "name": "engine_type",
          "type": "VARCHAR(32)",
          "pk": false,
          "not_null": true,
          "default": null
        },
        {
          "name": "domain",
          "type": "VARCHAR(64)",
          "pk": false,
          "not_null": true,
          "default": null
        },
        {
          "name": "endpoint",
          "type": "VARCHAR(256)",
          "pk": false,
          "not_null": true,
          "default": null
        },
        {
          "name": "version",
          "type": "VARCHAR(32)",
          "pk": false,
          "not_null": false,
          "default": null
        },
        {
          "name": "quota_tokens_per_day",
          "type": "INTEGER",
          "pk": false,
          "not_null": false,
          "default": null
        },
        {
          "name": "quota_used_today",
          "type": "INTEGER",
          "pk": false,
          "not_null": false,
          "default": null
        },
        {
          "name": "quota_reset_at",
          "type": "DATETIME",
          "pk": false,
          "not_null": false,
          "default": null
        },
        {
          "name": "latency_ms",
          "type": "FLOAT",
          "pk": false,
          "not_null": false,
          "default": null
        },
        {
          "name": "cost_per_call",
          "type": "FLOAT",
          "pk": false,
          "not_null": false,
          "default": null
        },
        {
          "name": "enabled",
          "type": "BOOLEAN",
          "pk": false,
          "not_null": false,
          "default": null
        },
        {
          "name": "last_used",
          "type": "DATETIME",
          "pk": false,
          "not_null": false,
          "default": null
        },
        {
          "name": "created_at",
          "type": "DATETIME",
          "pk": false,
          "not_null": false,
          "default": null
        },
        {
          "name": "updated_at",
          "type": "DATETIME",
          "pk": false,
          "not_null": false,
          "default": null
        }
      ],
      "foreign_keys": []
    },
    {
      "name": "events",
      "rows": 0,
      "status": "EMPTY (READY)",
      "module": "unknown",
      "columns": [
        {
          "name": "id",
          "type": "INTEGER",
          "pk": true,
          "not_null": true,
          "default": null
        },
        {
          "name": "source",
          "type": "VARCHAR(64)",
          "pk": false,
          "not_null": true,
          "default": null
        },
        {
          "name": "event_type",
          "type": "VARCHAR(64)",
          "pk": false,
          "not_null": true,
          "default": null
        },
        {
          "name": "payload",
          "type": "TEXT",
          "pk": false,
          "not_null": false,
          "default": null
        },
        {
          "name": "created_at",
          "type": "DATETIME",
          "pk": false,
          "not_null": false,
          "default": null
        }
      ],
      "foreign_keys": []
    },
    {
      "name": "feromona_events",
      "rows": 0,
      "status": "EMPTY (READY)",
      "module": "unknown",
      "columns": [
        {
          "name": "id",
          "type": "INTEGER",
          "pk": true,
          "not_null": true,
          "default": null
        },
        {
          "name": "type",
          "type": "VARCHAR(64)",
          "pk": false,
          "not_null": true,
          "default": null
        },
        {
          "name": "intensity",
          "type": "INTEGER",
          "pk": false,
          "not_null": false,
          "default": null
        },
        {
          "name": "module",
          "type": "VARCHAR(64)",
          "pk": false,
          "not_null": true,
          "default": null
        },
        {
          "name": "payload",
          "type": "TEXT",
          "pk": false,
          "not_null": false,
          "default": null
        },
        {
          "name": "timestamp",
          "type": "DATETIME",
          "pk": false,
          "not_null": false,
          "default": null
        }
      ],
      "foreign_keys": []
    },
    {
      "name": "fluzo_signals",
      "rows": 0,
      "status": "EMPTY (READY)",
      "module": "switch",
      "columns": [
        {
          "name": "id",
          "type": "INTEGER",
          "pk": true,
          "not_null": true,
          "default": null
        },
        {
          "name": "timestamp",
          "type": "DATETIME",
          "pk": false,
          "not_null": false,
          "default": null
        },
        {
          "name": "cpu_load_1m",
          "type": "FLOAT",
          "pk": false,
          "not_null": false,
          "default": null
        },
        {
          "name": "mem_pct",
          "type": "FLOAT",
          "pk": false,
          "not_null": false,
          "default": null
        },
        {
          "name": "on_ac",
          "type": "BOOLEAN",
          "pk": false,
          "not_null": false,
          "default": null
        },
        {
          "name": "battery_pct",
          "type": "INTEGER",
          "pk": false,
          "not_null": false,
          "default": null
        },
        {
          "name": "profile",
          "type": "VARCHAR(32)",
          "pk": false,
          "not_null": false,
          "default": null
        }
      ],
      "foreign_keys": []
    },
    {
      "name": "forensic_ledger",
      "rows": 0,
      "status": "EMPTY (READY)",
      "module": "unknown",
      "columns": [
        {
          "name": "id",
          "type": "INTEGER",
          "pk": true,
          "not_null": true,
          "default": null
        },
        {
          "name": "event",
          "type": "VARCHAR(255)",
          "pk": false,
          "not_null": true,
          "default": null
        },
        {
          "name": "payload",
          "type": "TEXT",
          "pk": false,
          "not_null": false,
          "default": null
        },
        {
          "name": "hash",
          "type": "VARCHAR(64)",
          "pk": false,
          "not_null": true,
          "default": null
        },
        {
          "name": "created_at",
          "type": "DATETIME",
          "pk": false,
          "not_null": false,
          "default": null
        }
      ],
      "foreign_keys": []
    },
    {
      "name": "hermes_ingest",
      "rows": 0,
      "status": "EMPTY (READY)",
      "module": "unknown",
      "columns": [
        {
          "name": "id",
          "type": "INTEGER",
          "pk": true,
          "not_null": true,
          "default": null
        },
        {
          "name": "path",
          "type": "VARCHAR(512)",
          "pk": false,
          "not_null": true,
          "default": null
        },
        {
          "name": "size_bytes",
          "type": "INTEGER",
          "pk": false,
          "not_null": false,
          "default": null
        },
        {
          "name": "duration_sec",
          "type": "FLOAT",
          "pk": false,
          "not_null": false,
          "default": null
        },
        {
          "name": "status",
          "type": "VARCHAR(32)",
          "pk": false,
          "not_null": false,
          "default": null
        },
        {
          "name": "created_at",
          "type": "DATETIME",
          "pk": false,
          "not_null": false,
          "default": null
        }
      ],
      "foreign_keys": []
    },
    {
      "name": "hijas_runtime",
      "rows": 21,
      "status": "ACTIVE",
      "module": "unknown",
      "columns": [
        {
          "name": "id",
          "type": "INTEGER",
          "pk": true,
          "not_null": true,
          "default": null
        },
        {
          "name": "name",
          "type": "VARCHAR(128)",
          "pk": false,
          "not_null": true,
          "default": null
        },
        {
          "name": "state",
          "type": "VARCHAR(32)",
          "pk": false,
          "not_null": false,
          "default": null
        },
        {
          "name": "pid",
          "type": "INTEGER",
          "pk": false,
          "not_null": false,
          "default": null
        },
        {
          "name": "last_heartbeat",
          "type": "DATETIME",
          "pk": false,
          "not_null": false,
          "default": null
        },
        {
          "name": "meta_json",
          "type": "TEXT",
          "pk": false,
          "not_null": false,
          "default": null
        },
        {
          "name": "birth_context",
          "type": "TEXT",
          "pk": false,
          "not_null": false,
          "default": null
        },
        {
          "name": "death_context",
          "type": "TEXT",
          "pk": false,
          "not_null": false,
          "default": null
        },
        {
          "name": "intent_type",
          "type": "VARCHAR(64)",
          "pk": false,
          "not_null": false,
          "default": null
        },
        {
          "name": "ttl",
          "type": "INTEGER",
          "pk": false,
          "not_null": false,
          "default": null
        },
        {
          "name": "killed_by",
          "type": "VARCHAR(128)",
          "pk": false,
          "not_null": false,
          "default": null
        },
        {
          "name": "purpose",
          "type": "VARCHAR(256)",
          "pk": false,
          "not_null": false,
          "default": null
        },
        {
          "name": "module_creator",
          "type": "VARCHAR(64)",
          "pk": false,
          "not_null": false,
          "default": null
        },
        {
          "name": "born_at",
          "type": "DATETIME",
          "pk": false,
          "not_null": false,
          "default": null
        },
        {
          "name": "died_at",
          "type": "DATETIME",
          "pk": false,
          "not_null": false,
          "default": null
        }
      ],
      "foreign_keys": []
    },
    {
      "name": "hijas_state",
      "rows": 0,
      "status": "EMPTY (READY)",
      "module": "unknown",
      "columns": [
        {
          "name": "id",
          "type": "INTEGER",
          "pk": true,
          "not_null": true,
          "default": null
        },
        {
          "name": "hija_id",
          "type": "VARCHAR(64)",
          "pk": false,
          "not_null": true,
          "default": null
        },
        {
          "name": "module",
          "type": "VARCHAR(64)",
          "pk": false,
          "not_null": true,
          "default": null
        },
        {
          "name": "status",
          "type": "VARCHAR(32)",
          "pk": false,
          "not_null": false,
          "default": null
        },
        {
          "name": "cpu_usage",
          "type": "FLOAT",
          "pk": false,
          "not_null": false,
          "default": null
        },
        {
          "name": "ram_usage",
          "type": "FLOAT",
          "pk": false,
          "not_null": false,
          "default": null
        },
        {
          "name": "pid",
          "type": "INTEGER",
          "pk": false,
          "not_null": false,
          "default": null
        },
        {
          "name": "created_at",
          "type": "DATETIME",
          "pk": false,
          "not_null": false,
          "default": null
        },
        {
          "name": "updated_at",
          "type": "DATETIME",
          "pk": false,
          "not_null": false,
          "default": null
        }
      ],
      "foreign_keys": []
    },
    {
      "name": "hormiga_state",
      "rows": 0,
      "status": "EMPTY (READY)",
      "module": "hormiguero",
      "columns": [
        {
          "name": "id",
          "type": "INTEGER",
          "pk": true,
          "not_null": true,
          "default": null
        },
        {
          "name": "ant_id",
          "type": "VARCHAR(64)",
          "pk": false,
          "not_null": true,
          "default": null
        },
        {
          "name": "role",
          "type": "VARCHAR(32)",
          "pk": false,
          "not_null": true,
          "default": null
        },
        {
          "name": "status",
          "type": "VARCHAR(20)",
          "pk": false,
          "not_null": false,
          "default": null
        },
        {
          "name": "last_scan_at",
          "type": "DATETIME",
          "pk": false,
          "not_null": false,
          "default": null
        },
        {
          "name": "mutation_level",
          "type": "INTEGER",
          "pk": false,
          "not_null": false,
          "default": null
        },
        {
          "name": "cpu_percent",
          "type": "FLOAT",
          "pk": false,
          "not_null": false,
          "default": null
        },
        {
          "name": "ram_percent",
          "type": "FLOAT",
          "pk": false,
          "not_null": false,
          "default": null
        },
        {
          "name": "created_at",
          "type": "DATETIME",
          "pk": false,
          "not_null": false,
          "default": null
        },
        {
          "name": "updated_at",
          "type": "DATETIME",
          "pk": false,
          "not_null": false,
          "default": null
        }
      ],
      "foreign_keys": []
    },
    {
      "name": "ia_decisions",
      "rows": 2,
      "status": "ACTIVE",
      "module": "switch",
      "columns": [
        {
          "name": "id",
          "type": "INTEGER",
          "pk": true,
          "not_null": true,
          "default": null
        },
        {
          "name": "prompt_hash",
          "type": "VARCHAR(64)",
          "pk": false,
          "not_null": true,
          "default": null
        },
        {
          "name": "provider",
          "type": "VARCHAR(50)",
          "pk": false,
          "not_null": true,
          "default": null
        },
        {
          "name": "task_type",
          "type": "VARCHAR(50)",
          "pk": false,
          "not_null": false,
          "default": null
        },
        {
          "name": "prompt",
          "type": "TEXT",
          "pk": false,
          "not_null": true,
          "default": null
        },
        {
          "name": "response",
          "type": "TEXT",
          "pk": false,
          "not_null": false,
          "default": null
        },
        {
          "name": "latency_ms",
          "type": "INTEGER",
          "pk": false,
          "not_null": false,
          "default": null
        },
        {
          "name": "success",
          "type": "BOOLEAN",
          "pk": false,
          "not_null": false,
          "default": null
        },
        {
          "name": "confidence",
          "type": "FLOAT",
          "pk": false,
          "not_null": false,
          "default": null
        },
        {
          "name": "meta_json",
          "type": "TEXT",
          "pk": false,
          "not_null": false,
          "default": null
        },
        {
          "name": "created_at",
          "type": "DATETIME",
          "pk": false,
          "not_null": false,
          "default": null
        }
      ],
      "foreign_keys": []
    },
    {
      "name": "incidents",
      "rows": 0,
      "status": "EMPTY (READY)",
      "module": "hormiguero",
      "columns": [
        {
          "name": "id",
          "type": "INTEGER",
          "pk": true,
          "not_null": true,
          "default": null
        },
        {
          "name": "ant_id",
          "type": "VARCHAR(64)",
          "pk": false,
          "not_null": true,
          "default": null
        },
        {
          "name": "incident_type",
          "type": "VARCHAR(64)",
          "pk": false,
          "not_null": true,
          "default": null
        },
        {
          "name": "severity",
          "type": "VARCHAR(20)",
          "pk": false,
          "not_null": false,
          "default": null
        },
        {
          "name": "location",
          "type": "VARCHAR(255)",
          "pk": false,
          "not_null": false,
          "default": null
        },
        {
          "name": "details",
          "type": "TEXT",
          "pk": false,
          "not_null": false,
          "default": null
        },
        {
          "name": "status",
          "type": "VARCHAR(20)",
          "pk": false,
          "not_null": false,
          "default": null
        },
        {
          "name": "detected_at",
          "type": "DATETIME",
          "pk": false,
          "not_null": false,
          "default": null
        },
        {
          "name": "resolved_at",
          "type": "DATETIME",
          "pk": false,
          "not_null": false,
          "default": null
        },
        {
          "name": "queen_decision",
          "type": "VARCHAR(255)",
          "pk": false,
          "not_null": false,
          "default": null
        }
      ],
      "foreign_keys": []
    },
    {
      "name": "intents_log",
      "rows": 0,
      "status": "EMPTY (READY)",
      "module": "unknown",
      "columns": [
        {
          "name": "id",
          "type": "INTEGER",
          "pk": true,
          "not_null": true,
          "default": null
        },
        {
          "name": "source",
          "type": "VARCHAR(64)",
          "pk": false,
          "not_null": true,
          "default": null
        },
        {
          "name": "payload_json",
          "type": "TEXT",
          "pk": false,
          "not_null": true,
          "default": null
        },
        {
          "name": "created_at",
          "type": "DATETIME",
          "pk": false,
          "not_null": false,
          "default": null
        },
        {
          "name": "processed_by_madre_at",
          "type": "DATETIME",
          "pk": false,
          "not_null": false,
          "default": null
        },
        {
          "name": "result_status",
          "type": "VARCHAR(32)",
          "pk": false,
          "not_null": false,
          "default": null
        },
        {
          "name": "notes",
          "type": "TEXT",
          "pk": false,
          "not_null": false,
          "default": null
        }
      ],
      "foreign_keys": []
    },
    {
      "name": "local_models_v2",
      "rows": 2,
      "status": "ACTIVE",
      "module": "hermes",
      "columns": [
        {
          "name": "id",
          "type": "INTEGER",
          "pk": true,
          "not_null": true,
          "default": null
        },
        {
          "name": "name",
          "type": "VARCHAR(255)",
          "pk": false,
          "not_null": true,
          "default": null
        },
        {
          "name": "engine",
          "type": "VARCHAR(50)",
          "pk": false,
          "not_null": true,
          "default": null
        },
        {
          "name": "path",
          "type": "VARCHAR(512)",
          "pk": false,
          "not_null": true,
          "default": null
        },
        {
          "name": "size_bytes",
          "type": "INTEGER",
          "pk": false,
          "not_null": true,
          "default": null
        },
        {
          "name": "task_type",
          "type": "VARCHAR(50)",
          "pk": false,
          "not_null": true,
          "default": null
        },
        {
          "name": "max_context",
          "type": "INTEGER",
          "pk": false,
          "not_null": false,
          "default": null
        },
        {
          "name": "enabled",
          "type": "BOOLEAN",
          "pk": false,
          "not_null": false,
          "default": null
        },
        {
          "name": "last_used_at",
          "type": "DATETIME",
          "pk": false,
          "not_null": false,
          "default": null
        },
        {
          "name": "usage_count",
          "type": "INTEGER",
          "pk": false,
          "not_null": false,
          "default": null
        },
        {
          "name": "compatibility",
          "type": "VARCHAR(64)",
          "pk": false,
          "not_null": false,
          "default": null
        },
        {
          "name": "meta_info",
          "type": "TEXT",
          "pk": false,
          "not_null": false,
          "default": null
        },
        {
          "name": "created_at",
          "type": "DATETIME",
          "pk": false,
          "not_null": false,
          "default": null
        },
        {
          "name": "updated_at",
          "type": "DATETIME",
          "pk": false,
          "not_null": false,
          "default": null
        }
      ],
      "foreign_keys": []
    },
    {
      "name": "madre_actions",
      "rows": 0,
      "status": "EMPTY (READY)",
      "module": "unknown",
      "columns": [
        {
          "name": "id",
          "type": "INTEGER",
          "pk": true,
          "not_null": true,
          "default": null
        },
        {
          "name": "module",
          "type": "VARCHAR(64)",
          "pk": false,
          "not_null": true,
          "default": null
        },
        {
          "name": "action",
          "type": "VARCHAR(64)",
          "pk": false,
          "not_null": true,
          "default": null
        },
        {
          "name": "reason",
          "type": "VARCHAR(255)",
          "pk": false,
          "not_null": false,
          "default": null
        },
        {
          "name": "created_at",
          "type": "DATETIME",
          "pk": false,
          "not_null": false,
          "default": null
        }
      ],
      "foreign_keys": []
    },
    {
      "name": "madre_policies",
      "rows": 0,
      "status": "EMPTY (READY)",
      "module": "unknown",
      "columns": [
        {
          "name": "id",
          "type": "INTEGER",
          "pk": true,
          "not_null": true,
          "default": null
        },
        {
          "name": "module",
          "type": "VARCHAR(64)",
          "pk": false,
          "not_null": true,
          "default": null
        },
        {
          "name": "error_threshold",
          "type": "INTEGER",
          "pk": false,
          "not_null": false,
          "default": null
        },
        {
          "name": "idle_seconds",
          "type": "INTEGER",
          "pk": false,
          "not_null": false,
          "default": null
        },
        {
          "name": "enable_autosuspend",
          "type": "BOOLEAN",
          "pk": false,
          "not_null": false,
          "default": null
        },
        {
          "name": "created_at",
          "type": "DATETIME",
          "pk": false,
          "not_null": false,
          "default": null
        },
        {
          "name": "updated_at",
          "type": "DATETIME",
          "pk": false,
          "not_null": false,
          "default": null
        }
      ],
      "foreign_keys": []
    },
    {
      "name": "model_registry",
      "rows": 0,
      "status": "EMPTY (READY)",
      "module": "hermes",
      "columns": [
        {
          "name": "id",
          "type": "INTEGER",
          "pk": true,
          "not_null": true,
          "default": null
        },
        {
          "name": "name",
          "type": "VARCHAR(255)",
          "pk": false,
          "not_null": true,
          "default": null
        },
        {
          "name": "path",
          "type": "VARCHAR(500)",
          "pk": false,
          "not_null": true,
          "default": null
        },
        {
          "name": "provider",
          "type": "VARCHAR(50)",
          "pk": false,
          "not_null": true,
          "default": null
        },
        {
          "name": "type",
          "type": "VARCHAR(50)",
          "pk": false,
          "not_null": true,
          "default": null
        },
        {
          "name": "size_bytes",
          "type": "INTEGER",
          "pk": false,
          "not_null": true,
          "default": null
        },
        {
          "name": "tags",
          "type": "TEXT",
          "pk": false,
          "not_null": false,
          "default": null
        },
        {
          "name": "last_used",
          "type": "DATETIME",
          "pk": false,
          "not_null": false,
          "default": null
        },
        {
          "name": "score",
          "type": "FLOAT",
          "pk": false,
          "not_null": false,
          "default": null
        },
        {
          "name": "available",
          "type": "BOOLEAN",
          "pk": false,
          "not_null": false,
          "default": null
        },
        {
          "name": "meta_json",
          "type": "TEXT",
          "pk": false,
          "not_null": false,
          "default": null
        },
        {
          "name": "created_at",
          "type": "DATETIME",
          "pk": false,
          "not_null": false,
          "default": null
        },
        {
          "name": "updated_at",
          "type": "DATETIME",
          "pk": false,
          "not_null": false,
          "default": null
        }
      ],
      "foreign_keys": []
    },
    {
      "name": "model_usage_stats",
      "rows": 2,
      "status": "ACTIVE",
      "module": "switch",
      "columns": [
        {
          "name": "id",
          "type": "INTEGER",
          "pk": true,
          "not_null": true,
          "default": null
        },
        {
          "name": "model_or_cli_name",
          "type": "VARCHAR(255)",
          "pk": false,
          "not_null": true,
          "default": null
        },
        {
          "name": "kind",
          "type": "VARCHAR(20)",
          "pk": false,
          "not_null": true,
          "default": null
        },
        {
          "name": "task_type",
          "type": "VARCHAR(50)",
          "pk": false,
          "not_null": true,
          "default": null
        },
        {
          "name": "tokens_used",
          "type": "INTEGER",
          "pk": false,
          "not_null": false,
          "default": null
        },
        {
          "name": "latency_ms",
          "type": "INTEGER",
          "pk": false,
          "not_null": false,
          "default": null
        },
        {
          "name": "success",
          "type": "BOOLEAN",
          "pk": false,
          "not_null": false,
          "default": null
        },
        {
          "name": "error_message",
          "type": "VARCHAR(500)",
          "pk": false,
          "not_null": false,
          "default": null
        },
        {
          "name": "user_id",
          "type": "VARCHAR(100)",
          "pk": false,
          "not_null": false,
          "default": null
        },
        {
          "name": "created_at",
          "type": "DATETIME",
          "pk": false,
          "not_null": false,
          "default": null
        }
      ],
      "foreign_keys": []
    },
    {
      "name": "models_local",
      "rows": 30,
      "status": "ACTIVE",
      "module": "unknown",
      "columns": [
        {
          "name": "id",
          "type": "INTEGER",
          "pk": true,
          "not_null": true,
          "default": null
        },
        {
          "name": "name",
          "type": "VARCHAR(255)",
          "pk": false,
          "not_null": true,
          "default": null
        },
        {
          "name": "path",
          "type": "VARCHAR(512)",
          "pk": false,
          "not_null": true,
          "default": null
        },
        {
          "name": "size_mb",
          "type": "INTEGER",
          "pk": false,
          "not_null": false,
          "default": null
        },
        {
          "name": "hash",
          "type": "VARCHAR(128)",
          "pk": false,
          "not_null": false,
          "default": null
        },
        {
          "name": "category",
          "type": "VARCHAR(64)",
          "pk": false,
          "not_null": false,
          "default": null
        },
        {
          "name": "status",
          "type": "VARCHAR(32)",
          "pk": false,
          "not_null": false,
          "default": null
        },
        {
          "name": "compatibility",
          "type": "VARCHAR(64)",
          "pk": false,
          "not_null": false,
          "default": null
        },
        {
          "name": "downloaded_at",
          "type": "DATETIME",
          "pk": false,
          "not_null": false,
          "default": null
        },
        {
          "name": "updated_at",
          "type": "DATETIME",
          "pk": false,
          "not_null": false,
          "default": null
        }
      ],
      "foreign_keys": []
    },
    {
      "name": "models_remote_cli",
      "rows": 0,
      "status": "EMPTY (READY)",
      "module": "unknown",
      "columns": [
        {
          "name": "id",
          "type": "INTEGER",
          "pk": true,
          "not_null": true,
          "default": null
        },
        {
          "name": "provider",
          "type": "VARCHAR(128)",
          "pk": false,
          "not_null": true,
          "default": null
        },
        {
          "name": "token",
          "type": "VARCHAR(256)",
          "pk": false,
          "not_null": true,
          "default": null
        },
        {
          "name": "limit_daily",
          "type": "INTEGER",
          "pk": false,
          "not_null": false,
          "default": null
        },
        {
          "name": "limit_weekly",
          "type": "INTEGER",
          "pk": false,
          "not_null": false,
          "default": null
        },
        {
          "name": "renew_at",
          "type": "DATETIME",
          "pk": false,
          "not_null": false,
          "default": null
        },
        {
          "name": "task_type",
          "type": "VARCHAR(64)",
          "pk": false,
          "not_null": false,
          "default": null
        },
        {
          "name": "status",
          "type": "VARCHAR(32)",
          "pk": false,
          "not_null": false,
          "default": null
        },
        {
          "name": "created_at",
          "type": "DATETIME",
          "pk": false,
          "not_null": false,
          "default": null
        },
        {
          "name": "updated_at",
          "type": "DATETIME",
          "pk": false,
          "not_null": false,
          "default": null
        }
      ],
      "foreign_keys": []
    },
    {
      "name": "module_health",
      "rows": 0,
      "status": "EMPTY (READY)",
      "module": "switch",
      "columns": [
        {
          "name": "id",
          "type": "INTEGER",
          "pk": true,
          "not_null": true,
          "default": null
        },
        {
          "name": "module",
          "type": "VARCHAR(50)",
          "pk": false,
          "not_null": true,
          "default": null
        },
        {
          "name": "status",
          "type": "VARCHAR(20)",
          "pk": false,
          "not_null": false,
          "default": null
        },
        {
          "name": "last_ping",
          "type": "DATETIME",
          "pk": false,
          "not_null": false,
          "default": null
        },
        {
          "name": "error_count",
          "type": "INTEGER",
          "pk": false,
          "not_null": false,
          "default": null
        },
        {
          "name": "uptime_seconds",
          "type": "FLOAT",
          "pk": false,
          "not_null": false,
          "default": null
        },
        {
          "name": "updated_at",
          "type": "DATETIME",
          "pk": false,
          "not_null": false,
          "default": null
        }
      ],
      "foreign_keys": []
    },
    {
      "name": "operator_browser_task",
      "rows": 0,
      "status": "EMPTY (READY)",
      "module": "operator",
      "columns": [
        {
          "name": "id",
          "type": "INTEGER",
          "pk": true,
          "not_null": true,
          "default": null
        },
        {
          "name": "session_id",
          "type": "VARCHAR(64)",
          "pk": false,
          "not_null": true,
          "default": null
        },
        {
          "name": "url",
          "type": "VARCHAR(500)",
          "pk": false,
          "not_null": true,
          "default": null
        },
        {
          "name": "status",
          "type": "VARCHAR(50)",
          "pk": false,
          "not_null": false,
          "default": null
        },
        {
          "name": "snapshot_path",
          "type": "VARCHAR(255)",
          "pk": false,
          "not_null": false,
          "default": null
        },
        {
          "name": "result",
          "type": "TEXT",
          "pk": false,
          "not_null": false,
          "default": null
        },
        {
          "name": "error",
          "type": "TEXT",
          "pk": false,
          "not_null": false,
          "default": null
        },
        {
          "name": "created_at",
          "type": "DATETIME",
          "pk": false,
          "not_null": false,
          "default": null
        },
        {
          "name": "executed_at",
          "type": "DATETIME",
          "pk": false,
          "not_null": false,
          "default": null
        }
      ],
      "foreign_keys": [
        {
          "column": "session_id",
          "references_table": "operator_session",
          "references_column": "session_id"
        }
      ]
    },
    {
      "name": "operator_jobs",
      "rows": 0,
      "status": "EMPTY (READY)",
      "module": "unknown",
      "columns": [
        {
          "name": "id",
          "type": "INTEGER",
          "pk": true,
          "not_null": true,
          "default": null
        },
        {
          "name": "job_id",
          "type": "VARCHAR(64)",
          "pk": false,
          "not_null": true,
          "default": null
        },
        {
          "name": "intent",
          "type": "VARCHAR(64)",
          "pk": false,
          "not_null": true,
          "default": null
        },
        {
          "name": "status",
          "type": "VARCHAR(32)",
          "pk": false,
          "not_null": false,
          "default": null
        },
        {
          "name": "payload",
          "type": "TEXT",
          "pk": false,
          "not_null": false,
          "default": null
        },
        {
          "name": "result",
          "type": "TEXT",
          "pk": false,
          "not_null": false,
          "default": null
        },
        {
          "name": "created_at",
          "type": "DATETIME",
          "pk": false,
          "not_null": false,
          "default": null
        },
        {
          "name": "updated_at",
          "type": "DATETIME",
          "pk": false,
          "not_null": false,
          "default": null
        }
      ],
      "foreign_keys": []
    },
    {
      "name": "operator_message",
      "rows": 0,
      "status": "EMPTY (READY)",
      "module": "operator",
      "columns": [
        {
          "name": "id",
          "type": "INTEGER",
          "pk": true,
          "not_null": true,
          "default": null
        },
        {
          "name": "session_id",
          "type": "VARCHAR(64)",
          "pk": false,
          "not_null": true,
          "default": null
        },
        {
          "name": "role",
          "type": "VARCHAR(50)",
          "pk": false,
          "not_null": true,
          "default": null
        },
        {
          "name": "content",
          "type": "TEXT",
          "pk": false,
          "not_null": true,
          "default": null
        },
        {
          "name": "message_metadata",
          "type": "TEXT",
          "pk": false,
          "not_null": false,
          "default": null
        },
        {
          "name": "created_at",
          "type": "DATETIME",
          "pk": false,
          "not_null": false,
          "default": null
        }
      ],
      "foreign_keys": [
        {
          "column": "session_id",
          "references_table": "operator_session",
          "references_column": "session_id"
        }
      ]
    },
    {
      "name": "operator_session",
      "rows": 16,
      "status": "ACTIVE",
      "module": "operator",
      "columns": [
        {
          "name": "id",
          "type": "INTEGER",
          "pk": true,
          "not_null": true,
          "default": null
        },
        {
          "name": "session_id",
          "type": "VARCHAR(64)",
          "pk": false,
          "not_null": true,
          "default": null
        },
        {
          "name": "user_id",
          "type": "VARCHAR(64)",
          "pk": false,
          "not_null": true,
          "default": null
        },
        {
          "name": "source",
          "type": "VARCHAR(50)",
          "pk": false,
          "not_null": true,
          "default": null
        },
        {
          "name": "created_at",
          "type": "DATETIME",
          "pk": false,
          "not_null": false,
          "default": null
        },
        {
          "name": "updated_at",
          "type": "DATETIME",
          "pk": false,
          "not_null": false,
          "default": null
        }
      ],
      "foreign_keys": []
    },
    {
      "name": "operator_switch_adjustment",
      "rows": 16,
      "status": "ACTIVE",
      "module": "unknown",
      "columns": [
        {
          "name": "id",
          "type": "INTEGER",
          "pk": true,
          "not_null": true,
          "default": null
        },
        {
          "name": "session_id",
          "type": "VARCHAR(64)",
          "pk": false,
          "not_null": true,
          "default": null
        },
        {
          "name": "message_id",
          "type": "INTEGER",
          "pk": false,
          "not_null": false,
          "default": null
        },
        {
          "name": "before_config",
          "type": "TEXT",
          "pk": false,
          "not_null": true,
          "default": null
        },
        {
          "name": "after_config",
          "type": "TEXT",
          "pk": false,
          "not_null": true,
          "default": null
        },
        {
          "name": "reason",
          "type": "TEXT",
          "pk": false,
          "not_null": true,
          "default": null
        },
        {
          "name": "applied",
          "type": "BOOLEAN",
          "pk": false,
          "not_null": false,
          "default": null
        },
        {
          "name": "created_at",
          "type": "DATETIME",
          "pk": false,
          "not_null": false,
          "default": null
        },
        {
          "name": "applied_at",
          "type": "DATETIME",
          "pk": false,
          "not_null": false,
          "default": null
        }
      ],
      "foreign_keys": [
        {
          "column": "message_id",
          "references_table": "operator_message",
          "references_column": "id"
        },
        {
          "column": "session_id",
          "references_table": "operator_session",
          "references_column": "session_id"
        }
      ]
    },
    {
      "name": "operator_tool_call",
      "rows": 0,
      "status": "EMPTY (READY)",
      "module": "operator",
      "columns": [
        {
          "name": "id",
          "type": "INTEGER",
          "pk": true,
          "not_null": true,
          "default": null
        },
        {
          "name": "message_id",
          "type": "INTEGER",
          "pk": false,
          "not_null": true,
          "default": null
        },
        {
          "name": "tool_name",
          "type": "VARCHAR(100)",
          "pk": false,
          "not_null": true,
          "default": null
        },
        {
          "name": "status",
          "type": "VARCHAR(50)",
          "pk": false,
          "not_null": false,
          "default": null
        },
        {
          "name": "duration_ms",
          "type": "INTEGER",
          "pk": false,
          "not_null": false,
          "default": null
        },
        {
          "name": "result",
          "type": "TEXT",
          "pk": false,
          "not_null": false,
          "default": null
        },
        {
          "name": "error",
          "type": "TEXT",
          "pk": false,
          "not_null": false,
          "default": null
        },
        {
          "name": "created_at",
          "type": "DATETIME",
          "pk": false,
          "not_null": false,
          "default": null
        }
      ],
      "foreign_keys": [
        {
          "column": "message_id",
          "references_table": "operator_message",
          "references_column": "id"
        }
      ]
    },
    {
      "name": "pheromone_log",
      "rows": 0,
      "status": "EMPTY (READY)",
      "module": "unknown",
      "columns": [
        {
          "name": "id",
          "type": "INTEGER",
          "pk": true,
          "not_null": true,
          "default": null
        },
        {
          "name": "pheromone_type",
          "type": "VARCHAR(64)",
          "pk": false,
          "not_null": true,
          "default": null
        },
        {
          "name": "intensity",
          "type": "INTEGER",
          "pk": false,
          "not_null": false,
          "default": null
        },
        {
          "name": "source_incident_ids",
          "type": "TEXT",
          "pk": false,
          "not_null": false,
          "default": null
        },
        {
          "name": "madre_intent_id",
          "type": "VARCHAR(64)",
          "pk": false,
          "not_null": false,
          "default": null
        },
        {
          "name": "switch_consultation_id",
          "type": "VARCHAR(64)",
          "pk": false,
          "not_null": false,
          "default": null
        },
        {
          "name": "payload",
          "type": "TEXT",
          "pk": false,
          "not_null": false,
          "default": null
        },
        {
          "name": "created_at",
          "type": "DATETIME",
          "pk": false,
          "not_null": false,
          "default": null
        },
        {
          "name": "executed_at",
          "type": "DATETIME",
          "pk": false,
          "not_null": false,
          "default": null
        }
      ],
      "foreign_keys": []
    },
    {
      "name": "power_events",
      "rows": 0,
      "status": "EMPTY (READY)",
      "module": "unknown",
      "columns": [
        {
          "name": "id",
          "type": "INTEGER",
          "pk": true,
          "not_null": true,
          "default": null
        },
        {
          "name": "module",
          "type": "VARCHAR(64)",
          "pk": false,
          "not_null": true,
          "default": null
        },
        {
          "name": "action",
          "type": "VARCHAR(32)",
          "pk": false,
          "not_null": true,
          "default": null
        },
        {
          "name": "reason",
          "type": "VARCHAR(255)",
          "pk": false,
          "not_null": false,
          "default": null
        },
        {
          "name": "cpu_usage",
          "type": "FLOAT",
          "pk": false,
          "not_null": false,
          "default": null
        },
        {
          "name": "ram_usage",
          "type": "FLOAT",
          "pk": false,
          "not_null": false,
          "default": null
        },
        {
          "name": "activity_score",
          "type": "FLOAT",
          "pk": false,
          "not_null": false,
          "default": null
        },
        {
          "name": "timestamp",
          "type": "DATETIME",
          "pk": false,
          "not_null": false,
          "default": null
        }
      ],
      "foreign_keys": []
    },
    {
      "name": "reports",
      "rows": 0,
      "status": "EMPTY (READY)",
      "module": "madre",
      "columns": [
        {
          "name": "id",
          "type": "INTEGER",
          "pk": true,
          "not_null": true,
          "default": null
        },
        {
          "name": "task_id",
          "type": "VARCHAR(36)",
          "pk": false,
          "not_null": true,
          "default": null
        },
        {
          "name": "report_type",
          "type": "VARCHAR(50)",
          "pk": false,
          "not_null": true,
          "default": null
        },
        {
          "name": "summary",
          "type": "TEXT",
          "pk": false,
          "not_null": false,
          "default": null
        },
        {
          "name": "details",
          "type": "TEXT",
          "pk": false,
          "not_null": false,
          "default": null
        },
        {
          "name": "metrics",
          "type": "TEXT",
          "pk": false,
          "not_null": false,
          "default": null
        },
        {
          "name": "created_at",
          "type": "DATETIME",
          "pk": false,
          "not_null": false,
          "default": null
        }
      ],
      "foreign_keys": [
        {
          "column": "task_id",
          "references_table": "tasks",
          "references_column": "uuid"
        }
      ]
    },
    {
      "name": "routing_events",
      "rows": 1,
      "status": "ACTIVE",
      "module": "switch",
      "columns": [
        {
          "name": "id",
          "type": "INTEGER",
          "pk": true,
          "not_null": true,
          "default": null
        },
        {
          "name": "timestamp",
          "type": "DATETIME",
          "pk": false,
          "not_null": false,
          "default": null
        },
        {
          "name": "trace_id",
          "type": "VARCHAR(36)",
          "pk": false,
          "not_null": true,
          "default": null
        },
        {
          "name": "route_type",
          "type": "VARCHAR(50)",
          "pk": false,
          "not_null": true,
          "default": null
        },
        {
          "name": "provider_id",
          "type": "VARCHAR(128)",
          "pk": false,
          "not_null": true,
          "default": null
        },
        {
          "name": "score",
          "type": "FLOAT",
          "pk": false,
          "not_null": false,
          "default": null
        },
        {
          "name": "reasoning_short",
          "type": "VARCHAR(255)",
          "pk": false,
          "not_null": false,
          "default": null
        }
      ],
      "foreign_keys": []
    },
    {
      "name": "sandbox_exec",
      "rows": 0,
      "status": "EMPTY (READY)",
      "module": "unknown",
      "columns": [
        {
          "name": "id",
          "type": "INTEGER",
          "pk": true,
          "not_null": true,
          "default": null
        },
        {
          "name": "action",
          "type": "VARCHAR(128)",
          "pk": false,
          "not_null": true,
          "default": null
        },
        {
          "name": "status",
          "type": "VARCHAR(32)",
          "pk": false,
          "not_null": false,
          "default": null
        },
        {
          "name": "duration_ms",
          "type": "FLOAT",
          "pk": false,
          "not_null": false,
          "default": null
        },
        {
          "name": "error",
          "type": "TEXT",
          "pk": false,
          "not_null": false,
          "default": null
        },
        {
          "name": "created_at",
          "type": "DATETIME",
          "pk": false,
          "not_null": false,
          "default": null
        }
      ],
      "foreign_keys": []
    },
    {
      "name": "scheduler_history",
      "rows": 0,
      "status": "EMPTY (READY)",
      "module": "unknown",
      "columns": [
        {
          "name": "id",
          "type": "INTEGER",
          "pk": true,
          "not_null": true,
          "default": null
        },
        {
          "name": "timestamp",
          "type": "DATETIME",
          "pk": false,
          "not_null": false,
          "default": null
        },
        {
          "name": "action",
          "type": "VARCHAR(64)",
          "pk": false,
          "not_null": true,
          "default": null
        },
        {
          "name": "reason",
          "type": "TEXT",
          "pk": false,
          "not_null": false,
          "default": null
        },
        {
          "name": "metrics",
          "type": "TEXT",
          "pk": false,
          "not_null": false,
          "default": null
        }
      ],
      "foreign_keys": []
    },
    {
      "name": "shub_analysis",
      "rows": 0,
      "status": "EMPTY (READY)",
      "module": "shub",
      "columns": [
        {
          "name": "id",
          "type": "INTEGER",
          "pk": true,
          "not_null": true,
          "default": null
        },
        {
          "name": "track_id",
          "type": "INTEGER",
          "pk": false,
          "not_null": true,
          "default": null
        },
        {
          "name": "rms",
          "type": "FLOAT",
          "pk": false,
          "not_null": false,
          "default": null
        },
        {
          "name": "peak",
          "type": "FLOAT",
          "pk": false,
          "not_null": false,
          "default": null
        },
        {
          "name": "lufs",
          "type": "FLOAT",
          "pk": false,
          "not_null": false,
          "default": null
        },
        {
          "name": "noise_floor",
          "type": "FLOAT",
          "pk": false,
          "not_null": false,
          "default": null
        },
        {
          "name": "dynamic_range",
          "type": "FLOAT",
          "pk": false,
          "not_null": false,
          "default": null
        },
        {
          "name": "clipping",
          "type": "INTEGER",
          "pk": false,
          "not_null": false,
          "default": null
        },
        {
          "name": "notes",
          "type": "TEXT",
          "pk": false,
          "not_null": false,
          "default": null
        },
        {
          "name": "created_at",
          "type": "DATETIME",
          "pk": false,
          "not_null": false,
          "default": null
        }
      ],
      "foreign_keys": [
        {
          "column": "track_id",
          "references_table": "shub_tracks",
          "references_column": "id"
        }
      ]
    },
    {
      "name": "shub_fx_chains",
      "rows": 0,
      "status": "EMPTY (READY)",
      "module": "unknown",
      "columns": [
        {
          "name": "id",
          "type": "INTEGER",
          "pk": true,
          "not_null": true,
          "default": null
        },
        {
          "name": "track_id",
          "type": "INTEGER",
          "pk": false,
          "not_null": true,
          "default": null
        },
        {
          "name": "chain_name",
          "type": "VARCHAR(255)",
          "pk": false,
          "not_null": true,
          "default": null
        },
        {
          "name": "steps_json",
          "type": "TEXT",
          "pk": false,
          "not_null": true,
          "default": null
        },
        {
          "name": "created_at",
          "type": "DATETIME",
          "pk": false,
          "not_null": false,
          "default": null
        }
      ],
      "foreign_keys": [
        {
          "column": "track_id",
          "references_table": "shub_tracks",
          "references_column": "id"
        }
      ]
    },
    {
      "name": "shub_presets",
      "rows": 0,
      "status": "EMPTY (READY)",
      "module": "unknown",
      "columns": [
        {
          "name": "id",
          "type": "INTEGER",
          "pk": true,
          "not_null": true,
          "default": null
        },
        {
          "name": "fx_chain_id",
          "type": "INTEGER",
          "pk": false,
          "not_null": true,
          "default": null
        },
        {
          "name": "rpp_snippet",
          "type": "TEXT",
          "pk": false,
          "not_null": false,
          "default": null
        },
        {
          "name": "version",
          "type": "VARCHAR(32)",
          "pk": false,
          "not_null": false,
          "default": null
        },
        {
          "name": "created_at",
          "type": "DATETIME",
          "pk": false,
          "not_null": false,
          "default": null
        }
      ],
      "foreign_keys": [
        {
          "column": "fx_chain_id",
          "references_table": "shub_fx_chains",
          "references_column": "id"
        }
      ]
    },
    {
      "name": "shub_projects",
      "rows": 0,
      "status": "EMPTY (READY)",
      "module": "shub",
      "columns": [
        {
          "name": "id",
          "type": "INTEGER",
          "pk": true,
          "not_null": true,
          "default": null
        },
        {
          "name": "project_id",
          "type": "VARCHAR(64)",
          "pk": false,
          "not_null": true,
          "default": null
        },
        {
          "name": "name",
          "type": "VARCHAR(255)",
          "pk": false,
          "not_null": true,
          "default": null
        },
        {
          "name": "sample_rate",
          "type": "INTEGER",
          "pk": false,
          "not_null": false,
          "default": null
        },
        {
          "name": "created_at",
          "type": "DATETIME",
          "pk": false,
          "not_null": false,
          "default": null
        },
        {
          "name": "updated_at",
          "type": "DATETIME",
          "pk": false,
          "not_null": false,
          "default": null
        }
      ],
      "foreign_keys": []
    },
    {
      "name": "shub_tracks",
      "rows": 0,
      "status": "EMPTY (READY)",
      "module": "shub",
      "columns": [
        {
          "name": "id",
          "type": "INTEGER",
          "pk": true,
          "not_null": true,
          "default": null
        },
        {
          "name": "project_id",
          "type": "VARCHAR(64)",
          "pk": false,
          "not_null": true,
          "default": null
        },
        {
          "name": "name",
          "type": "VARCHAR(255)",
          "pk": false,
          "not_null": true,
          "default": null
        },
        {
          "name": "role",
          "type": "VARCHAR(64)",
          "pk": false,
          "not_null": false,
          "default": null
        },
        {
          "name": "file_path",
          "type": "VARCHAR(512)",
          "pk": false,
          "not_null": false,
          "default": null
        },
        {
          "name": "duration_sec",
          "type": "FLOAT",
          "pk": false,
          "not_null": false,
          "default": null
        },
        {
          "name": "created_at",
          "type": "DATETIME",
          "pk": false,
          "not_null": false,
          "default": null
        }
      ],
      "foreign_keys": [
        {
          "column": "project_id",
          "references_table": "shub_projects",
          "references_column": "project_id"
        }
      ]
    },
    {
      "name": "spawns",
      "rows": 0,
      "status": "EMPTY (READY)",
      "module": "madre",
      "columns": [
        {
          "name": "id",
          "type": "INTEGER",
          "pk": true,
          "not_null": true,
          "default": null
        },
        {
          "name": "uuid",
          "type": "VARCHAR(36)",
          "pk": false,
          "not_null": true,
          "default": null
        },
        {
          "name": "name",
          "type": "VARCHAR(255)",
          "pk": false,
          "not_null": true,
          "default": null
        },
        {
          "name": "cmd",
          "type": "VARCHAR(500)",
          "pk": false,
          "not_null": true,
          "default": null
        },
        {
          "name": "pid",
          "type": "INTEGER",
          "pk": false,
          "not_null": false,
          "default": null
        },
        {
          "name": "status",
          "type": "VARCHAR(20)",
          "pk": false,
          "not_null": false,
          "default": null
        },
        {
          "name": "started_at",
          "type": "DATETIME",
          "pk": false,
          "not_null": false,
          "default": null
        },
        {
          "name": "ended_at",
          "type": "DATETIME",
          "pk": false,
          "not_null": false,
          "default": null
        },
        {
          "name": "exit_code",
          "type": "INTEGER",
          "pk": false,
          "not_null": false,
          "default": null
        },
        {
          "name": "stdout",
          "type": "TEXT",
          "pk": false,
          "not_null": false,
          "default": null
        },
        {
          "name": "stderr",
          "type": "TEXT",
          "pk": false,
          "not_null": false,
          "default": null
        },
        {
          "name": "parent_task_id",
          "type": "VARCHAR(36)",
          "pk": false,
          "not_null": false,
          "default": null
        },
        {
          "name": "created_at",
          "type": "DATETIME",
          "pk": false,
          "not_null": false,
          "default": null
        }
      ],
      "foreign_keys": [
        {
          "column": "parent_task_id",
          "references_table": "tasks",
          "references_column": "uuid"
        }
      ]
    },
    {
      "name": "switch_queue_v2",
      "rows": 0,
      "status": "EMPTY (READY)",
      "module": "switch",
      "columns": [
        {
          "name": "id",
          "type": "INTEGER",
          "pk": true,
          "not_null": true,
          "default": null
        },
        {
          "name": "source",
          "type": "VARCHAR(64)",
          "pk": false,
          "not_null": true,
          "default": null
        },
        {
          "name": "priority",
          "type": "INTEGER",
          "pk": false,
          "not_null": false,
          "default": null
        },
        {
          "name": "task_type",
          "type": "VARCHAR(50)",
          "pk": false,
          "not_null": true,
          "default": null
        },
        {
          "name": "payload_hash",
          "type": "VARCHAR(64)",
          "pk": false,
          "not_null": true,
          "default": null
        },
        {
          "name": "status",
          "type": "VARCHAR(32)",
          "pk": false,
          "not_null": false,
          "default": null
        },
        {
          "name": "created_at",
          "type": "DATETIME",
          "pk": false,
          "not_null": false,
          "default": null
        },
        {
          "name": "started_at",
          "type": "DATETIME",
          "pk": false,
          "not_null": false,
          "default": null
        },
        {
          "name": "finished_at",
          "type": "DATETIME",
          "pk": false,
          "not_null": false,
          "default": null
        },
        {
          "name": "result_size",
          "type": "INTEGER",
          "pk": false,
          "not_null": false,
          "default": null
        },
        {
          "name": "error_message",
          "type": "VARCHAR(500)",
          "pk": false,
          "not_null": false,
          "default": null
        }
      ],
      "foreign_keys": []
    },
    {
      "name": "system_events",
      "rows": 21,
      "status": "ACTIVE",
      "module": "unknown",
      "columns": [
        {
          "name": "id",
          "type": "INTEGER",
          "pk": true,
          "not_null": true,
          "default": null
        },
        {
          "name": "timestamp",
          "type": "DATETIME",
          "pk": false,
          "not_null": false,
          "default": null
        },
        {
          "name": "source",
          "type": "VARCHAR(64)",
          "pk": false,
          "not_null": true,
          "default": null
        },
        {
          "name": "event_type",
          "type": "VARCHAR(64)",
          "pk": false,
          "not_null": true,
          "default": null
        },
        {
          "name": "payload",
          "type": "TEXT",
          "pk": false,
          "not_null": false,
          "default": null
        },
        {
          "name": "severity",
          "type": "VARCHAR(16)",
          "pk": false,
          "not_null": false,
          "default": null
        }
      ],
      "foreign_keys": []
    },
    {
      "name": "system_state",
      "rows": 0,
      "status": "EMPTY (READY)",
      "module": "unknown",
      "columns": [
        {
          "name": "id",
          "type": "INTEGER",
          "pk": true,
          "not_null": true,
          "default": null
        },
        {
          "name": "key",
          "type": "VARCHAR(128)",
          "pk": false,
          "not_null": true,
          "default": null
        },
        {
          "name": "value",
          "type": "TEXT",
          "pk": false,
          "not_null": false,
          "default": null
        },
        {
          "name": "updated_at",
          "type": "DATETIME",
          "pk": false,
          "not_null": false,
          "default": null
        },
        {
          "name": "memory_pressure",
          "type": "FLOAT",
          "pk": false,
          "not_null": false,
          "default": null
        },
        {
          "name": "cpu_pressure",
          "type": "FLOAT",
          "pk": false,
          "not_null": false,
          "default": null
        },
        {
          "name": "switch_queue_level",
          "type": "FLOAT",
          "pk": false,
          "not_null": false,
          "default": null
        },
        {
          "name": "hermes_update_required",
          "type": "BOOLEAN",
          "pk": false,
          "not_null": false,
          "default": null
        },
        {
          "name": "shub_pipeline_state",
          "type": "VARCHAR(64)",
          "pk": false,
          "not_null": false,
          "default": null
        },
        {
          "name": "operator_active",
          "type": "BOOLEAN",
          "pk": false,
          "not_null": false,
          "default": null
        },
        {
          "name": "system_load_score",
          "type": "FLOAT",
          "pk": false,
          "not_null": false,
          "default": null
        },
        {
          "name": "model_rotation_state",
          "type": "VARCHAR(128)",
          "pk": false,
          "not_null": false,
          "default": null
        },
        {
          "name": "audio_pipeline_state",
          "type": "VARCHAR(128)",
          "pk": false,
          "not_null": false,
          "default": null
        },
        {
          "name": "pending_tasks",
          "type": "INTEGER",
          "pk": false,
          "not_null": false,
          "default": null
        },
        {
          "name": "active_children",
          "type": "INTEGER",
          "pk": false,
          "not_null": false,
          "default": null
        },
        {
          "name": "last_operator_activity",
          "type": "DATETIME",
          "pk": false,
          "not_null": false,
          "default": null
        },
        {
          "name": "power_mode",
          "type": "VARCHAR(32)",
          "pk": false,
          "not_null": false,
          "default": null
        }
      ],
      "foreign_keys": []
    },
    {
      "name": "task_queue",
      "rows": 0,
      "status": "EMPTY (READY)",
      "module": "unknown",
      "columns": [
        {
          "name": "id",
          "type": "INTEGER",
          "pk": true,
          "not_null": true,
          "default": null
        },
        {
          "name": "source",
          "type": "VARCHAR(64)",
          "pk": false,
          "not_null": true,
          "default": null
        },
        {
          "name": "priority",
          "type": "INTEGER",
          "pk": false,
          "not_null": false,
          "default": null
        },
        {
          "name": "payload",
          "type": "TEXT",
          "pk": false,
          "not_null": true,
          "default": null
        },
        {
          "name": "status",
          "type": "VARCHAR(32)",
          "pk": false,
          "not_null": false,
          "default": null
        },
        {
          "name": "enqueued_at",
          "type": "DATETIME",
          "pk": false,
          "not_null": false,
          "default": null
        },
        {
          "name": "dequeued_at",
          "type": "DATETIME",
          "pk": false,
          "not_null": false,
          "default": null
        }
      ],
      "foreign_keys": []
    },
    {
      "name": "tasks",
      "rows": 0,
      "status": "EMPTY (READY)",
      "module": "madre",
      "columns": [
        {
          "name": "id",
          "type": "INTEGER",
          "pk": true,
          "not_null": true,
          "default": null
        },
        {
          "name": "uuid",
          "type": "VARCHAR(36)",
          "pk": false,
          "not_null": true,
          "default": null
        },
        {
          "name": "name",
          "type": "VARCHAR(255)",
          "pk": false,
          "not_null": true,
          "default": null
        },
        {
          "name": "module",
          "type": "VARCHAR(50)",
          "pk": false,
          "not_null": true,
          "default": null
        },
        {
          "name": "action",
          "type": "VARCHAR(100)",
          "pk": false,
          "not_null": true,
          "default": null
        },
        {
          "name": "status",
          "type": "VARCHAR(20)",
          "pk": false,
          "not_null": false,
          "default": null
        },
        {
          "name": "created_at",
          "type": "DATETIME",
          "pk": false,
          "not_null": false,
          "default": null
        },
        {
          "name": "updated_at",
          "type": "DATETIME",
          "pk": false,
          "not_null": false,
          "default": null
        },
        {
          "name": "result",
          "type": "TEXT",
          "pk": false,
          "not_null": false,
          "default": null
        },
        {
          "name": "error",
          "type": "TEXT",
          "pk": false,
          "not_null": false,
          "default": null
        }
      ],
      "foreign_keys": []
    },
    {
      "name": "tokens_usage",
      "rows": 0,
      "status": "EMPTY (READY)",
      "module": "unknown",
      "columns": [
        {
          "name": "id",
          "type": "INTEGER",
          "pk": true,
          "not_null": true,
          "default": null
        },
        {
          "name": "token_id",
          "type": "VARCHAR(256)",
          "pk": false,
          "not_null": true,
          "default": null
        },
        {
          "name": "used_at",
          "type": "DATETIME",
          "pk": false,
          "not_null": false,
          "default": null
        },
        {
          "name": "used_count",
          "type": "INTEGER",
          "pk": false,
          "not_null": false,
          "default": null
        },
        {
          "name": "source",
          "type": "VARCHAR(64)",
          "pk": false,
          "not_null": false,
          "default": null
        }
      ],
      "foreign_keys": []
    }
  ]
}