{
  "version": "9.0",
  "generated_at": "2025-12-22T11:30:11.691128+00:00",
  "outdir": "docs/audit/20251222T075806Z_autonomy_evidence",
  "source_files": {
    "health_results": "health_results.json",
    "e2e_flows": "e2e_flows.json",
    "pytest_summary": "pytest_summary.json (optional)"
  },
  "metrics": {
    "health_core_pct": {
      "value": 100.0,
      "status": "ok",
      "reason": "9/9 services healthy",
      "source": "health_results.json"
    },
    "contract_coherence_pct": {
      "value": 100.0,
      "status": "ok",
      "reason": "3/3 flows passed",
      "source": "e2e_flows.json"
    },
    "tests_p0_pct": {
      "value": 0.0,
      "status": "ok",
      "reason": "No P0 tests executed (integration tests require VX11_INTEGRATION=1)",
      "source": "pytest_summary.json"
    },
    "Estabilidad_operativa_pct": {
      "value": 70.0,
      "status": "ok",
      "formula": "0.4*health_core_pct + 0.3*tests_p0_pct + 0.3*contract_coherence_pct",
      "inputs": {
        "health_core_pct": 100.0,
        "tests_p0_pct": 0.0,
        "contract_coherence_pct": 100.0
      },
      "source": "formula (derived)"
    },
    "evidence_coverage_pct": {
      "value": 100.0,
      "status": "ok",
      "reason": "4/4 metrics with real evidence",
      "source": "derived"
    }
  },
  "verdicts": {
    "autonomy_operational": true,
    "all_flows_pass": true,
    "infrastructure_healthy": true
  }
}